lab7_1/rom.v
`timescale 1ns/1ps
module rom
    #(parameter Width = 8,
    parameter Depth = 5)(
    input oe,
    input cs_n,
    input [Depth-1:0] addr,
    output reg [Width-1:0] data
);

reg [Width-1:0] memory [0:2**Depth-1];


always @(*) begin
    case ({cs_n, oe})
        2'b01: data <= memory[addr];
        default: data <= 'bz;
    endcase
end

endmodule

lab7_1/rom_tb.v
`timescale 1ns / 1ps

module tb_rom ();
    parameter Width = 8;
    parameter Depth = 5;
    reg oe_reg;
    reg cs_n_reg;
    reg [Depth-1:0] addr_reg;
    wire [Width-1:0] data_wire;
    reg [7:0] exp_values [5'h0:5'h1F];
    reg [Width - 1:0] temp_data_reg;
    integer i;

   
    rom #(.Width(Width), .Depth(Depth)) rom_inst (
        .oe(oe_reg),
        .cs_n(cs_n_reg),
        .addr(addr_reg),
        .data(data_wire)
    );

    initial begin
        $dumpfile("test.vcd");
        $dumpvars(0, tb_rom);
        $vcdpluson;
     
        $readmemh("rom_data.hex", rom_inst.memory);

        test_memory_initialization();

        test_unspecified_locations();

        scramble_and_write_bytes();

        test_memory_scrambling();

        print_memory_contents();

      
        $finish;
    end

    task test_memory_initialization;
        begin
            
            exp_values[5'h04] = 8'h58;
            exp_values[5'h05] = 8'hED;
            exp_values[5'h06] = 8'hB7;
            exp_values[5'h07] = 8'h34;
            exp_values[5'h08] = 8'hC9;
            exp_values[5'h09] = 8'h8F;
            exp_values[5'h0A] = 8'hA0;
            exp_values[5'h0B] = 8'h9B;
            exp_values[5'h0C] = 8'h65;
            exp_values[5'h0D] = 8'h11;
            exp_values[5'h0E] = 8'h03;
            exp_values[5'h0F] = 8'h4C;
            exp_values[5'h10] = 8'hDA;
            exp_values[5'h11] = 8'h7E;
            exp_values[5'h12] = 8'hF2;
            exp_values[5'h13] = 8'h26;
            exp_values[5'h14] = 8'h86;
            exp_values[5'h15] = 8'h95;
            exp_values[5'h16] = 8'hFD;
            exp_values[5'h17] = 8'hB1;
            exp_values[5'h1C] = 8'h12;
            exp_values[5'h1D] = 8'hAF;
            exp_values[5'h1E] = 8'h33;

            for (i = 0; i < 32; i = i + 1) begin
                oe_reg = 1'b1;
                cs_n_reg = 1'b0;
                addr_reg = i;
                #10;

                if (data_wire !== exp_values[i]) begin
                    $display("Memory Initialization Test: FAILED at address %0h, expected: %0h, got: %0h", i, exp_values[i], data_wire);
                end else begin
                    $display("Memory Initialization Test: PASSED at address %0h, expected: %0h, got: %0h", i, exp_values[i], data_wire);
                end
            end
        end
    endtask

    task test_unspecified_locations; 
        begin 
            for (i=24; i<28; i=i+1) begin 
                addr_reg=i; 
                oe_reg=1'b1; 
                cs_n_reg=1'b0; 
                #10; 
                if (data_wire !== 8'hFF) begin 
                    $display("Unspecified Locations Test: FAILED at address %0h, expected: X, got: %0h", i, data_wire); 
                end else begin 
                    $display("Unspecified Locations Test: PASSED at address %0h, expected: X, got: X", i); 
                end
            end
        end
    endtask

    task scramble_and_write_bytes;
        begin
            for (i = 0; i < 8; i = i + 1) begin
                addr_reg = 5'h10 + i;
                oe_reg = 1'b1;
                cs_n_reg = 1'b0;
                #10;
                temp_data_reg = {data_wire[0], data_wire[7], data_wire[1], data_wire[6], data_wire[2], data_wire[5], data_wire[3], data_wire[4]};
                oe_reg = 1'b0;
                #10;
               
                exp_values[addr_reg] = temp_data_reg;
                rom_inst.memory[addr_reg] = temp_data_reg;
            end
        end
    endtask

    task test_memory_scrambling;
        begin 

            exp_values[5'h10] = 8'h73;

            for (i = 0; i < 8; i = i + 1) begin
                addr_reg = 5'h10 + i;
                oe_reg = 1'b1;
                cs_n_reg = 1'b0;
                #10;

                if (data_wire !== exp_values[addr_reg]) begin
                    $display("Memory Scrambling Test: FAILED at address %0h, expected: %0h, got: %0h", 5'h10 + i, exp_values[addr_reg], data_wire);
                end else begin
                    $display("Memory Scrambling Test: PASSED at address %0h, expected: %0h, got: %0h", 5'h10 + i, exp_values[addr_reg], data_wire);
                end
            end
        end
    endtask

    task print_memory_contents;
        begin
            for (i = 0; i < 32; i = i + 1) begin
                addr_reg = i;
                oe_reg = 1'b1;
                cs_n_reg = 1'b0;
                #10;

                $display("Memory Contents at address %0h: %0h", i, data_wire);
            end
        end
    endtask

endmodule

lab7_1/test.vcd
$date
	Fri Apr 21 00:13:10 2023
$end

$version
	Synopsys VCS version N-2017.12-SP2-9_Full64
$end

$timescale
	1ps
$end

$comment Csum: 1 af3713b2d0a1b083 $end


$scope module tb_rom $end
$var reg 1 ! oe_reg $end
$var reg 1 " cs_n_reg $end
$var reg 5 # addr_reg [4:0] $end
$var wire 8 $ data_wire [7:0] $end
$var reg 8 % temp_data_reg [7:0] $end
$var integer 32 & i $end

$scope task test_memory_initialization $end
$upscope $end


$scope task test_unspecified_locations $end
$upscope $end


$scope task scramble_and_write_bytes $end
$upscope $end


$scope task test_memory_scrambling $end
$upscope $end


$scope task print_memory_contents $end
$upscope $end


$scope module rom_inst $end
$var wire 1 ' oe $end
$var wire 1 ( cs_n $end
$var wire 5 ) addr [4:0] $end
$var reg 8 * data [7:0] $end
$upscope $end

$upscope $end

$enddefinitions $end

#0
$dumpvars
0(
0"
1'
1!
b00000 )
b00000 #
bxxxxxxxx *
bxxxxxxxx $
b00000000000000000000000000000000 &
bxxxxxxxx %
$end
#10000
b00000000000000000000000000000001 &
b00001 #
b00001 )
#20000
b00000000000000000000000000000010 &
b00010 #
b00010 )
#30000
b00000000000000000000000000000011 &
b00011 #
b00011 )
#40000
b00000000000000000000000000000100 &
b00100 #
b00100 )
b01011000 *
b01011000 $
#50000
b00000000000000000000000000000101 &
b00101 #
b00101 )
b11101101 *
b11101101 $
#60000
b00000000000000000000000000000110 &
b00110 #
b00110 )
b10110111 *
b10110111 $
#70000
b00000000000000000000000000000111 &
b00111 #
b00111 )
b00110100 *
b00110100 $
#80000
b00000000000000000000000000001000 &
b01000 #
b01000 )
b11001001 *
b11001001 $
#90000
b00000000000000000000000000001001 &
b01001 #
b01001 )
b10001111 *
b10001111 $
#100000
b00000000000000000000000000001010 &
b01010 #
b01010 )
b10100000 *
b10100000 $
#110000
b00000000000000000000000000001011 &
b01011 #
b01011 )
b10011011 *
b10011011 $
#120000
b00000000000000000000000000001100 &
b01100 #
b01100 )
b01100101 *
b01100101 $
#130000
b00000000000000000000000000001101 &
b01101 #
b01101 )
b00010001 *
b00010001 $
#140000
b00000000000000000000000000001110 &
b01110 #
b01110 )
b00000011 *
b00000011 $
#150000
b00000000000000000000000000001111 &
b01111 #
b01111 )
b01001100 *
b01001100 $
#160000
b00000000000000000000000000010000 &
b10000 #
b10000 )
b11011010 *
b11011010 $
#170000
b00000000000000000000000000010001 &
b10001 #
b10001 )
b01111110 *
b01111110 $
#180000
b00000000000000000000000000010010 &
b10010 #
b10010 )
b11110010 *
b11110010 $
#190000
b00000000000000000000000000010011 &
b10011 #
b10011 )
b00100110 *
b00100110 $
#200000
b00000000000000000000000000010100 &
b10100 #
b10100 )
b10000110 *
b10000110 $
#210000
b00000000000000000000000000010101 &
b10101 #
b10101 )
b10010101 *
b10010101 $
#220000
b00000000000000000000000000010110 &
b10110 #
b10110 )
b11111101 *
b11111101 $
#230000
b00000000000000000000000000010111 &
b10111 #
b10111 )
b10110001 *
b10110001 $
#240000
b00000000000000000000000000011000 &
b11000 #
b11000 )
bxxxxxxxx *
bxxxxxxxx $
#250000
b00000000000000000000000000011001 &
b11001 #
b11001 )
#260000
b00000000000000000000000000011010 &
b11010 #
b11010 )
#270000
b00000000000000000000000000011011 &
b11011 #
b11011 )
#280000
b00000000000000000000000000011100 &
b11100 #
b11100 )
b00010010 *
b00010010 $
#290000
b00000000000000000000000000011101 &
b11101 #
b11101 )
b10101111 *
b10101111 $
#300000
b00000000000000000000000000011110 &
b11110 #
b11110 )
b00110011 *
b00110011 $
#310000
b00000000000000000000000000011111 &
b11111 #
b11111 )
bxxxxxxxx *
bxxxxxxxx $
#320000
b00000000000000000000000000100000 &
b00000000000000000000000000011000 &
b11000 #
b11000 )
#330000
b00000000000000000000000000011001 &
b11001 #
b11001 )
#340000
b00000000000000000000000000011010 &
b11010 #
b11010 )
#350000
b00000000000000000000000000011011 &
b11011 #
b11011 )
#360000
b00000000000000000000000000011100 &
b00000000000000000000000000000000 &
b10000 #
b10000 )
b11011010 *
b11011010 $
#370000
b01110011 %
0!
0'
bzzzzzzzz *
bzzzzzzzz $
#380000
b00000000000000000000000000000001 &
b10001 #
b10001 )
1!
1'
b01111110 *
b01111110 $
#390000
b00111111 %
0!
0'
bzzzzzzzz *
bzzzzzzzz $
#400000
b00000000000000000000000000000010 &
b10010 #
b10010 )
1!
1'
b11110010 *
b11110010 $
#410000
b01110101 %
0!
0'
bzzzzzzzz *
bzzzzzzzz $
#420000
b00000000000000000000000000000011 &
b10011 #
b10011 )
1!
1'
b00100110 *
b00100110 $
#430000
b00101100 %
0!
0'
bzzzzzzzz *
bzzzzzzzz $
#440000
b00000000000000000000000000000100 &
b10100 #
b10100 )
1!
1'
b10000110 *
b10000110 $
#450000
b01101000 %
0!
0'
bzzzzzzzz *
bzzzzzzzz $
#460000
b00000000000000000000000000000101 &
b10101 #
b10101 )
1!
1'
b10010101 *
b10010101 $
#470000
b11001001 %
0!
0'
bzzzzzzzz *
bzzzzzzzz $
#480000
b00000000000000000000000000000110 &
b10110 #
b10110 )
1!
1'
b11111101 *
b11111101 $
#490000
b11011111 %
0!
0'
bzzzzzzzz *
bzzzzzzzz $
#500000
b00000000000000000000000000000111 &
b10111 #
b10111 )
1!
1'
b10110001 *
b10110001 $
#510000
b11000101 %
0!
0'
bzzzzzzzz *
bzzzzzzzz $
#520000
b00000000000000000000000000001000 &
b00000000000000000000000000000000 &
b10000 #
b10000 )
1!
1'
b01110011 *
b01110011 $
#530000
b00000000000000000000000000000001 &
b10001 #
b10001 )
b00111111 *
b00111111 $
#540000
b00000000000000000000000000000010 &
b10010 #
b10010 )
b01110101 *
b01110101 $
#550000
b00000000000000000000000000000011 &
b10011 #
b10011 )
b00101100 *
b00101100 $
#560000
b00000000000000000000000000000100 &
b10100 #
b10100 )
b01101000 *
b01101000 $
#570000
b00000000000000000000000000000101 &
b10101 #
b10101 )
b11001001 *
b11001001 $
#580000
b00000000000000000000000000000110 &
b10110 #
b10110 )
b11011111 *
b11011111 $
#590000
b00000000000000000000000000000111 &
b10111 #
b10111 )
b11000101 *
b11000101 $
#600000
b00000000000000000000000000001000 &
b00000000000000000000000000000000 &
b00000 #
b00000 )
bxxxxxxxx *
bxxxxxxxx $
#610000
b00000000000000000000000000000001 &
b00001 #
b00001 )
#620000
b00000000000000000000000000000010 &
b00010 #
b00010 )
#630000
b00000000000000000000000000000011 &
b00011 #
b00011 )
#640000
b00000000000000000000000000000100 &
b00100 #
b00100 )
b01011000 *
b01011000 $
#650000
b00000000000000000000000000000101 &
b00101 #
b00101 )
b11101101 *
b11101101 $
#660000
b00000000000000000000000000000110 &
b00110 #
b00110 )
b10110111 *
b10110111 $
#670000
b00000000000000000000000000000111 &
b00111 #
b00111 )
b00110100 *
b00110100 $
#680000
b00000000000000000000000000001000 &
b01000 #
b01000 )
b11001001 *
b11001001 $
#690000
b00000000000000000000000000001001 &
b01001 #
b01001 )
b10001111 *
b10001111 $
#700000
b00000000000000000000000000001010 &
b01010 #
b01010 )
b10100000 *
b10100000 $
#710000
b00000000000000000000000000001011 &
b01011 #
b01011 )
b10011011 *
b10011011 $
#720000
b00000000000000000000000000001100 &
b01100 #
b01100 )
b01100101 *
b01100101 $
#730000
b00000000000000000000000000001101 &
b01101 #
b01101 )
b00010001 *
b00010001 $
#740000
b00000000000000000000000000001110 &
b01110 #
b01110 )
b00000011 *
b00000011 $
#750000
b00000000000000000000000000001111 &
b01111 #
b01111 )
b01001100 *
b01001100 $
#760000
b00000000000000000000000000010000 &
b10000 #
b10000 )
b01110011 *
b01110011 $
#770000
b00000000000000000000000000010001 &
b10001 #
b10001 )
b00111111 *
b00111111 $
#780000
b00000000000000000000000000010010 &
b10010 #
b10010 )
b01110101 *
b01110101 $
#790000
b00000000000000000000000000010011 &
b10011 #
b10011 )
b00101100 *
b00101100 $
#800000
b00000000000000000000000000010100 &
b10100 #
b10100 )
b01101000 *
b01101000 $
#810000
b00000000000000000000000000010101 &
b10101 #
b10101 )
b11001001 *
b11001001 $
#820000
b00000000000000000000000000010110 &
b10110 #
b10110 )
b11011111 *
b11011111 $
#830000
b00000000000000000000000000010111 &
b10111 #
b10111 )
b11000101 *
b11000101 $
#840000
b00000000000000000000000000011000 &
b11000 #
b11000 )
bxxxxxxxx *
bxxxxxxxx $
#850000
b00000000000000000000000000011001 &
b11001 #
b11001 )
#860000
b00000000000000000000000000011010 &
b11010 #
b11010 )
#870000
b00000000000000000000000000011011 &
b11011 #
b11011 )
#880000
b00000000000000000000000000011100 &
b11100 #
b11100 )
b00010010 *
b00010010 $
#890000
b00000000000000000000000000011101 &
b11101 #
b11101 )
b10101111 *
b10101111 $
#900000
b00000000000000000000000000011110 &
b11110 #
b11110 )
b00110011 *
b00110011 $
#910000
b00000000000000000000000000011111 &
b11111 #
b11111 )
bxxxxxxxx *
bxxxxxxxx $
#920000
b00000000000000000000000000100000 &
